rusticlone/__init__.py
rusticlone/cli.py
rusticlone/helpers/__init__.py
rusticlone/helpers/action.py
rusticlone/helpers/custom.py
rusticlone/helpers/formatting.py
rusticlone/helpers/notification.py
rusticlone/helpers/rclone.py
rusticlone/helpers/requirements.py
rusticlone/helpers/rustic.py
rusticlone/helpers/timer.py
rusticlone/processing/__init__.py
rusticlone/processing/atomic.py
rusticlone/processing/parallel.py
rusticlone/processing/profile.py
rusticlone/processing/sequential.py
rusticlone-1.6.0.dist-info/licenses/LICENSE
rusticlone-1.6.0.dist-info/METADATA
rusticlone-1.6.0.dist-info/WHEEL
rusticlone-1.6.0.dist-info/entry_points.txt
rusticlone-1.6.0.dist-info/top_level.txt
rusticlone-1.6.0.dist-info/RECORD
