Metadata-Version: 2.4
Name: rusticlone
Version: 1.6.0
Summary: 3-2-1 backups using Rustic and RClone
Author: AlphaJack
License-Expression: GPL-3.0-or-later
Project-URL: Homepage, https://github.com/AlphaJack/rusticlone
Project-URL: Issues, https://github.com/AlphaJack/rusticlone/issues
Project-URL: Repository, https://github.com/AlphaJack/rusticlone
Project-URL: Changelog, https://github.com/AlphaJack/rusticlone/blob/master/CHANGELOG.md
Classifier: Development Status :: 5 - Production/Stable
Classifier: Intended Audience :: End Users/Desktop
Classifier: Topic :: System :: Archiving :: Backup
Classifier: Environment :: Console
Classifier: Operating System :: OS Independent
Classifier: Programming Language :: Python :: 3
Requires-Python: >=3.11
License-File: LICENSE
Requires-Dist: configargparse
Requires-Dist: importlib-metadata
Dynamic: license-file
